aabd/__init__.py
aabd/ai/__init__.py
aabd/ai/face/__init__.py
aabd/ai/face/face_clip.py
aabd/ai/face/face_inference.py
aabd/ai/face/face_pyr.py
aabd/ai/face/face_quality_ediffiqa.py
aabd/ai/yolo/__init__.py
aabd/ai/yolo/pooled_gpu_model.py
aabd/ai/yolo/yolo.py
aabd/ai/yolo/yolo_util.py
aabd/base/__init__.py
aabd/base/cfg_loader.py
aabd/base/colors.py
aabd/base/download.py
aabd/base/enhance_dict.py
aabd/base/file_combo.py
aabd/base/gpu_util.py
aabd/base/hierarchy_match.py
aabd/base/load_config.py
aabd/base/log_config.py
aabd/base/log_setting.py
aabd/base/patched_logging.py
aabd/base/path_util.py
aabd/base/py_tools.py
aabd/base/time_util.py
aabd/base/timeit.py
aabd/base/tpm.py
aabd/image/AlibabaPuHuiTi-3-65-Medium.ttf
aabd/image/__init__.py
aabd/image/calc_coord.py
aabd/image/conv_coord.py
aabd/image/conv_img.py
aabd/image/coord.py
aabd/image/cv_draw.py
aabd/image/draw_image.py
aabd/image/image_converter.py
aabd/image/image_draw.py
aabd/image/image_number.py
aabd/image/img_in_img_pos.py
aabd/image/pil_draw.py
aabd/image/preprocess_image.py
aabd/image/read_image.py
aabd/mq/__init__.py
aabd/mq/channel.py
aabd/mq/kafka.py
aabd/mq/kafka_client.py
aabd/mq/rabbitmq.py
aabd/stream_chain/base_chain.py
aabd/stream_chain/base_nodes.py
aabd/stream_chain/chain_executor.py
aabd/stream_chain/chain_nodes.py
aabd/stream_chain/video2frames.py
aabd/video/__init__.py
aabd/video/cv_tools.py
aabd/video/grab_frame.py
aabd/video/random_frame.py
aabd/video/select_video_frames.py
aabd/video/video2frames.py
aabd-0.4.1.dist-info/METADATA
aabd-0.4.1.dist-info/WHEEL
aabd-0.4.1.dist-info/top_level.txt
aabd-0.4.1.dist-info/RECORD
